Metadata-Version: 1.0
Name: TradeInterface
Version: 0.2.8
Summary: a interface of simulate-trading stocks
Home-page: https://github.com/Inistlwq/TradeInterface
Author: cb_Lian
Author-email: 787162506@qq.com
License: MIT Licence
Keywords: pip,TradeInterface,trade,haizhi
Platform: any
